jupyter_eg_renderer/__init__.py
jupyter_eg_renderer/_version.py
jupyter_eg_renderer/example.py
jupyter_eg_renderer/static/extension.js
jupyter_eg_renderer/static/index.js
jupyter_eg_renderer/static/index.js.map
jupyter_eg_renderer-0.1.0a0.data/data/etc/jupyter/nbconfig/notebook.d/jupyter-eg-renderer.json
jupyter_eg_renderer-0.1.0a0.data/data/share/jupyter/nbextensions/jupyter-eg-renderer/extension.js
jupyter_eg_renderer-0.1.0a0.data/data/share/jupyter/nbextensions/jupyter-eg-renderer/index.js
jupyter_eg_renderer-0.1.0a0.data/data/share/jupyter/nbextensions/jupyter-eg-renderer/index.js.map
jupyter_eg_renderer-0.1.0a0.dist-info/METADATA
jupyter_eg_renderer-0.1.0a0.dist-info/WHEEL
jupyter_eg_renderer-0.1.0a0.dist-info/top_level.txt
jupyter_eg_renderer-0.1.0a0.dist-info/RECORD
